atlantic_server/__init__.py
atlantic_server/atl/__init__.py
atlantic_server/atl/admin.py
atlantic_server/atl/apps.py
atlantic_server/atl/models.py
atlantic_server/atl/serializers.py
atlantic_server/atl/urls.py
atlantic_server/atl/views.py
atlantic_server/com/__init__.py
atlantic_server/com/admin.py
atlantic_server/com/apps.py
atlantic_server/com/const.py
atlantic_server/com/models.py
atlantic_server/com/serializers.py
atlantic_server/com/urls.py
atlantic_server/com/views.py
atlantic_server/manage.py
atlantic_server/settings.py
atlantic_server/smd/__init__.py
atlantic_server/smd/admin.py
atlantic_server/smd/apps.py
atlantic_server/smd/documents/procedure.xml
atlantic_server/smd/gitdoc.py
atlantic_server/smd/models.py
atlantic_server/smd/serializers.py
atlantic_server/smd/urls.py
atlantic_server/smd/views.py
atlantic_server/urls.py
atlantic_server/wsgi.py
atlantic_server-0.3.5.dist-info/entry_points.txt
atlantic_server-0.3.5.dist-info/LICENSE
atlantic_server-0.3.5.dist-info/WHEEL
atlantic_server-0.3.5.dist-info/METADATA
atlantic_server-0.3.5.dist-info/RECORD
