Metadata-Version: 2.1
Name: atlantic-server
Version: 0.3.5
Summary: Server side of an application of an Aircraft Technical Log
License: MIT
Author: Matthieu Nué
Author-email: matthieu.nue@gmail.com
Requires-Python: >=3.7,<4.0
Classifier: License :: OSI Approved :: MIT License
Classifier: Programming Language :: Python :: 3
Classifier: Programming Language :: Python :: 3.7
Classifier: Programming Language :: Python :: 3.8
Requires-Dist: Django (>=2.2,<3.0)
Requires-Dist: cffi (>=1.14.0,<2.0.0)
Requires-Dist: django-filter (>=2,<3)
Requires-Dist: djangorestframework (>=3,<4)
Requires-Dist: drf-nested-routers (>=0.91,<0.92)
Requires-Dist: lxml (>=4,<5)
Requires-Dist: mysqlclient (>=2,<3)
Requires-Dist: pygit2 (>=1.2,<1.3)
Requires-Dist: wheel (>=0.35.1,<0.36.0)
